discoveryworld/ActionHistory.py
discoveryworld/ActionSuccess.py
discoveryworld/Agent.py
discoveryworld/DialogTree.py
discoveryworld/DiscoveryFeed.py
discoveryworld/DiscoveryWorldAPI.py
discoveryworld/JSONEncoder.py
discoveryworld/KnowledgeEvaluationTemplate.py
discoveryworld/KnowledgeScorer.py
discoveryworld/Layer.py
discoveryworld/ObjectMaker.py
discoveryworld/Pathfinding.py
discoveryworld/ScenarioMaker.py
discoveryworld/ScienceHelpers.py
discoveryworld/SpriteLibrary.py
discoveryworld/TaskScorer.py
discoveryworld/UUIDGenerator.py
discoveryworld/UserInterface.py
discoveryworld/World.py
discoveryworld/__init__.py
discoveryworld/constants.py
discoveryworld/version.py
discoveryworld/assets/spriteIndex.json
discoveryworld/assets/generated/flowerpot1_32.png
discoveryworld/assets/pixymoon/CuteRPG_Castle_New/32x32/CuteRPG_Castle_New.png
discoveryworld/assets/pixymoon/CuteRPG_Caves/32x32/CuteRPG_Caves.png
discoveryworld/assets/pixymoon/CuteRPG_Desert/32x32/CuteRPG_Desert_Inside.png
discoveryworld/assets/pixymoon/CuteRPG_Desert/32x32/CuteRPG_Desert_Outside_modified.png
discoveryworld/assets/pixymoon/CuteRPG_Enemies/Enemies_Sprite_Sheets/Enemy06_04.png
discoveryworld/assets/pixymoon/CuteRPG_Enemies/Enemies_Sprite_Sheets/Enemy06_04_greyscale.png
discoveryworld/assets/pixymoon/CuteRPG_Enemies/Enemies_Sprite_Sheets/Enemy10_2.png
discoveryworld/assets/pixymoon/CuteRPG_Enemies/Enemies_Sprite_Sheets/Enemy10_2_greyscale.png
discoveryworld/assets/pixymoon/CuteRPG_Enemies/Enemies_Sprite_Sheets/Enemy11_01.png
discoveryworld/assets/pixymoon/CuteRPG_Enemies/Enemies_Sprite_Sheets/Enemy11_01_greyscale.png
discoveryworld/assets/pixymoon/CuteRPG_Enemies/Enemies_Sprite_Sheets/Enemy14_03.png
discoveryworld/assets/pixymoon/CuteRPG_Enemies/Enemies_Sprite_Sheets/Enemy14_03_greyscale.png
discoveryworld/assets/pixymoon/CuteRPG_Enemies/Enemies_Sprite_Sheets/Enemy16_03.png
discoveryworld/assets/pixymoon/CuteRPG_Enemies/Enemies_Sprite_Sheets/Enemy16_03_greyscale.png
discoveryworld-0.0.2.dist-info/LICENSE.txt
discoveryworld-0.0.2.dist-info/METADATA
discoveryworld-0.0.2.dist-info/WHEEL
discoveryworld-0.0.2.dist-info/top_level.txt
discoveryworld-0.0.2.dist-info/RECORD
