Metadata-Version: 2.2
Name: discoveryworld
Version: 0.0.2
Summary: DiscoveryWorld - Making new discovery.
Home-page: https://github.com/allenai/discoveryworld
Author: Peter Jansen, Marc-Alexandre Côté
Classifier: Programming Language :: Python :: 3
Classifier: License :: OSI Approved :: Apache Software License
Classifier: Operating System :: POSIX :: Linux
Classifier: Operating System :: MacOS :: MacOS X
Requires-Python: >=3.8
License-File: LICENSE.txt
Requires-Dist: pygame
Requires-Dist: pathfinding
Requires-Dist: psutil
Requires-Dist: openai
Requires-Dist: numpy
Requires-Dist: termcolor
Requires-Dist: tiktoken
Requires-Dist: matplotlib
Dynamic: author
Dynamic: classifier
Dynamic: description
Dynamic: description-content-type
Dynamic: home-page
Dynamic: requires-dist
Dynamic: requires-python
Dynamic: summary
